ShenruLijieOpenstackZidonghuaBushu/README.md
ShenruLijieOpenstackZidonghuaBushu/__init__.py
ShenruLijieOpenstackZidonghuaBushu/__main__.py
ShenruLijieOpenstackZidonghuaBushu/file.epub
ShenruLijieOpenstackZidonghuaBushu/index.html
ShenruLijieOpenstackZidonghuaBushu/css/__init__.py
ShenruLijieOpenstackZidonghuaBushu/css/annotations.css
ShenruLijieOpenstackZidonghuaBushu/css/main.css
ShenruLijieOpenstackZidonghuaBushu/css/normalize.css
ShenruLijieOpenstackZidonghuaBushu/css/popup.css
ShenruLijieOpenstackZidonghuaBushu/font/__init__.py
ShenruLijieOpenstackZidonghuaBushu/font/fontello.eot
ShenruLijieOpenstackZidonghuaBushu/font/fontello.svg
ShenruLijieOpenstackZidonghuaBushu/font/fontello.ttf
ShenruLijieOpenstackZidonghuaBushu/font/fontello.woff
ShenruLijieOpenstackZidonghuaBushu/img/__init__.py
ShenruLijieOpenstackZidonghuaBushu/img/annotator-glyph-sprite.png
ShenruLijieOpenstackZidonghuaBushu/img/annotator-icon-sprite.png
ShenruLijieOpenstackZidonghuaBushu/img/apple-touch-icon.png
ShenruLijieOpenstackZidonghuaBushu/img/cancelfullscreen.png
ShenruLijieOpenstackZidonghuaBushu/img/close.png
ShenruLijieOpenstackZidonghuaBushu/img/fullscreen.png
ShenruLijieOpenstackZidonghuaBushu/img/loader.gif
ShenruLijieOpenstackZidonghuaBushu/img/menu-icon.png
ShenruLijieOpenstackZidonghuaBushu/img/save.png
ShenruLijieOpenstackZidonghuaBushu/img/saved.png
ShenruLijieOpenstackZidonghuaBushu/img/settings-s.png
ShenruLijieOpenstackZidonghuaBushu/img/settings.png
ShenruLijieOpenstackZidonghuaBushu/img/star.png
ShenruLijieOpenstackZidonghuaBushu/js/__init__.py
ShenruLijieOpenstackZidonghuaBushu/js/epub.js
ShenruLijieOpenstackZidonghuaBushu/js/epub.min.js
ShenruLijieOpenstackZidonghuaBushu/js/epub.min.map
ShenruLijieOpenstackZidonghuaBushu/js/hooks.min.js
ShenruLijieOpenstackZidonghuaBushu/js/hooks.min.map
ShenruLijieOpenstackZidonghuaBushu/js/reader.js
ShenruLijieOpenstackZidonghuaBushu/js/reader.js.map
ShenruLijieOpenstackZidonghuaBushu/js/reader.min.js
shenru_lijie_openstack_zidonghua_bushu-2024.3.3.0.dist-info/METADATA
shenru_lijie_openstack_zidonghua_bushu-2024.3.3.0.dist-info/WHEEL
shenru_lijie_openstack_zidonghua_bushu-2024.3.3.0.dist-info/entry_points.txt
shenru_lijie_openstack_zidonghua_bushu-2024.3.3.0.dist-info/top_level.txt
shenru_lijie_openstack_zidonghua_bushu-2024.3.3.0.dist-info/RECORD
